{
  "names": {
    "fr": "Lugulabre",
    "de": "Skelabra",
    "it": "Chandelure",
    "en": "Chandelure"
  },
  "national_id": 609,
  "types": [
    "Ghost",
    "Fire"
  ],
  "abilities": [
    {
      "name": "Flash Fire"
    },
    {
      "name": "Infiltrator",
      "hidden": true
    }
  ],
  "gender_ratios": {
    "male": 50.0,
    "female": 50.0
  },
  "catch_rate": 45,
  "egg_groups": [
    "Amorphous"
  ],
  "hatch_time": [
    5355,
    5609
  ],
  "height_us": "3'03\"",
  "height_eu": "1.0 m",
  "weight_us": "75.6 lbs.",
  "weight_eu": "34.3 kg",
  "base_exp_yield": 234,
  "leveling_rate": "Medium Slow",
  "ev_yield": {
    "hp": 0,
    "atk": 0,
    "def": 0,
    "sp_atk": 3,
    "sp_def": 0,
    "speed": 0
  },
  "color": "Black",
  "base_friendship": 70,
  "base_stats": {
    "hp": 60,
    "atk": 55,
    "def": 90,
    "sp_atk": 145,
    "sp_def": 90,
    "speed": 80
  },
  "learnset": [
    {
      "level": 0,
      "move": "Pain Split"
    },
    {
      "level": 0,
      "move": "Smog"
    },
    {
      "level": 0,
      "move": "Confuse Ray"
    },
    {
      "level": 0,
      "move": "Flame Burst"
    },
    {
      "level": 0,
      "move": "Hex"
    },
    {
      "tm": "TM04",
      "move": "Calm Mind"
    },
    {
      "tm": "TM06",
      "move": "Toxic"
    },
    {
      "tm": "TM10",
      "move": "Hidden Power"
    },
    {
      "tm": "TM11",
      "move": "Sunny Day"
    },
    {
      "tm": "TM12",
      "move": "Taunt"
    },
    {
      "tm": "TM15",
      "move": "Hyper Beam"
    },
    {
      "tm": "TM17",
      "move": "Protect"
    },
    {
      "tm": "TM21",
      "move": "Frustration"
    },
    {
      "tm": "TM22",
      "move": "Solar Beam"
    },
    {
      "tm": "TM27",
      "move": "Return"
    },
    {
      "tm": "TM29",
      "move": "Psychic"
    },
    {
      "tm": "TM30",
      "move": "Shadow Ball"
    },
    {
      "tm": "TM32",
      "move": "Double Team"
    },
    {
      "tm": "TM35",
      "move": "Flamethrower"
    },
    {
      "tm": "TM38",
      "move": "Fire Blast"
    },
    {
      "tm": "TM42",
      "move": "Facade"
    },
    {
      "tm": "TM43",
      "move": "Flame Charge"
    },
    {
      "tm": "TM44",
      "move": "Rest"
    },
    {
      "tm": "TM45",
      "move": "Attract"
    },
    {
      "tm": "TM46",
      "move": "Thief"
    },
    {
      "tm": "TM48",
      "move": "Round"
    },
    {
      "tm": "TM50",
      "move": "Overheat"
    },
    {
      "tm": "TM53",
      "move": "Energy Ball"
    },
    {
      "tm": "TM59",
      "move": "Incinerate"
    },
    {
      "tm": "TM61",
      "move": "Will-O-Wisp"
    },
    {
      "tm": "TM63",
      "move": "Embargo"
    },
    {
      "tm": "TM66",
      "move": "Payback"
    },
    {
      "tm": "TM68",
      "move": "Giga Impact"
    },
    {
      "tm": "TM70",
      "move": "Flash"
    },
    {
      "tm": "TM77",
      "move": "Psych Up"
    },
    {
      "tm": "TM85",
      "move": "Dream Eater"
    },
    {
      "tm": "TM87",
      "move": "Swagger"
    },
    {
      "tm": "TM88",
      "move": "Sleep Talk"
    },
    {
      "tm": "TM90",
      "move": "Substitute"
    },
    {
      "tm": "TM92",
      "move": "Trick Room"
    },
    {
      "tm": "TM97",
      "move": "Dark Pulse"
    },
    {
      "tm": "TM100",
      "move": "Confide"
    },
    {
      "parent": "Koffing",
      "move": "Clear Smog"
    },
    {
      "parent": "Weezing",
      "move": "Clear Smog"
    },
    {
      "parent": "Stunfisk",
      "move": "Endure"
    },
    {
      "parent": "Koffing",
      "move": "Haze"
    },
    {
      "parent": "Weezing",
      "move": "Haze"
    },
    {
      "parent": "Yamask",
      "move": "Haze"
    },
    {
      "parent": "Cofagrigus",
      "move": "Haze"
    },
    {
      "parent": "Slugma",
      "move": "Heat Wave"
    },
    {
      "parent": "Magcargo",
      "move": "Heat Wave"
    },
    {
      "parent": "Litwick",
      "move": "Heat Wave"
    },
    {
      "parent": "Lampent",
      "move": "Heat Wave"
    },
    {
      "parent": "Chandelure",
      "move": "Heat Wave"
    },
    {
      "parent": "Yamask",
      "move": "Power Split"
    },
    {
      "parent": "Cofagrigus",
      "move": "Power Split"
    }
  ],
  "evolution_from": "Lampent",
  "categories": {
    "en": "Luring Pokémon",
    "de": "Geleit"
  },
  "kanto_id": null,
  "johto_id": null,
  "hoenn_id": null,
  "sinnoh_id": null,
  "unova_id": 115,
  "kalos_id": 67,
  "alola_id": null,
  "mega_evolutions": [

  ],
  "evolutions": [

  ],
  "variations": [

  ],
  "pokedex_entries": {
    "Black": {
      "en": "It absorbs a spirit, which it then burns. By waving the flames on its arms, it puts its foes into a hypnotic trance.",
      "de": "Es saugt die Seelen seiner Opfer aus und verbrennt sie. Nutzt seine Arme als Pendel, um den Gegner zu hypnotisieren."
    },
    "White": {
      "en": "Being consumed in Chandelure's flame burns up the spirit, leaving the body behind.",
      "de": "Es saugt die Seele eines jeden auf, der in seinen Feuerkranz gerät, bis nur noch eine leere Hülle von ihm übrig ist."
    },
    "Black 2": {
      "en": "The spirits burned up in its ominous flame lose their way and wander this world forever.",
      "de": "Seelen, die das Feuer seiner schaurigen Flammen gekostet haben, irren bis ans Ende der Tage ziellos durch diese Welt."
    },
    "White 2": {
      "en": "The spirits burned up in its ominous flame lose their way and wander this world forever.",
      "de": "Seelen, die das Feuer seiner schaurigen Flammen gekostet haben, irren bis ans Ende der Tage ziellos durch diese Welt."
    },
    "X": {
      "en": "Being consumed in Chandelure's flame burns up the spirit, leaving the body behind.",
      "de": "Es saugt die Seele eines jeden auf, der in seinen Feuerkranz gerät, bis nur noch eine leere Hülle von ihm übrig ist."
    },
    "Y": {
      "en": "The spirits burned up in its ominous flame lose their way and wander this world forever.",
      "de": "Seelen, die das Feuer seiner schaurigen Flammen gekostet haben, irren bis ans Ende der Tage ziellos durch diese Welt."
    },
    "Omega Ruby": {
      "en": "Being consumed in Chandelure's flame burns up the spirit, leaving the body behind.",
      "de": "Seelen, die das Feuer seiner schaurigen Flammen gekostet haben, irren bis ans Ende der Tage ziellos durch diese Welt."
    },
    "Alpha Sapphire": {
      "en": "The spirits burned up in its ominous flame lose their way and wonder this world forever.",
      "de": "Seelen, die das Feuer seiner schaurigen Flammen gekostet haben, irren bis ans Ende der Tage ziellos durch diese Welt."
    }
  },
  "pokeathlon_stats": {
    "speed": [
      0,
      0
    ],
    "power": [
      0,
      0
    ],
    "stamina": [
      0,
      0
    ],
    "skill": [
      0,
      0
    ],
    "jump": [
      0,
      0
    ]
  }
}