{
  "names": {
    "fr": "Pitrouille",
    "de": "Irrbis",
    "it": "Pumpkaboo",
    "en": "Pumpkaboo"
  },
  "national_id": 710,
  "types": [
    "Ghost",
    "Grass"
  ],
  "abilities": [
    {
      "name": "Pickup"
    },
    {
      "name": "Insomnia",
      "hidden": true
    }
  ],
  "gender_ratios": {
    "male": 50.0,
    "female": 50.0
  },
  "catch_rate": 120,
  "egg_groups": [
    "Amorphous"
  ],
  "hatch_time": [
    5355,
    5609
  ],
  "height_us": "1'00\"",
  "height_eu": "0.3 m",
  "weight_us": "7.7 lbs.",
  "weight_eu": "3.5 kg",
  "base_exp_yield": 67,
  "leveling_rate": "Medium Fast",
  "ev_yield": {
    "hp": 0,
    "atk": 0,
    "def": 1,
    "sp_atk": 0,
    "sp_def": 0,
    "speed": 0
  },
  "color": "Brown",
  "base_friendship": 70,
  "base_stats": {
    "hp": 44,
    "atk": 66,
    "def": 70,
    "sp_atk": 44,
    "sp_def": 55,
    "speed": 56
  },
  "evolutions": [
    {
      "to": "Gourgeist",
      "trade": true
    }
  ],
  "categories": {
    "en": "Pumpkin Pokémon",
    "de": "Kürbis"
  },
  "kanto_id": null,
  "johto_id": null,
  "hoenn_id": null,
  "sinnoh_id": null,
  "unova_id": null,
  "kalos_id": 63,
  "alola_id": null,
  "mega_evolutions": [

  ],
  "evolution_from": null,
  "variation_names": {
    "en": "Small Size",
    "de": "Größe S"
  },
  "variations": [
    {
      "condition": "Inherited or Random",
      "image_suffix": "average",
      "names": {
        "en": "Average Size",
        "de": "Größe M"
      },
      "types": [
        "Ghost",
        "Grass"
      ],
      "height_us": "1'04\"",
      "height_eu": "0.4 m",
      "weight_us": "11.0 lbs.",
      "weight_eu": "5.0 kg",
      "base_stats": {
        "hp": 49,
        "atk": 66,
        "def": 70,
        "sp_atk": 44,
        "sp_def": 55,
        "speed": 51
      }
    },
    {
      "condition": "Inherited or Random",
      "image_suffix": "large",
      "names": {
        "en": "Large Size",
        "de": "Größe L"
      },
      "types": [
        "Ghost",
        "Grass"
      ],
      "height_us": "1'08\"",
      "height_eu": "0.5 m",
      "weight_us": "16.5 lbs.",
      "weight_eu": "7.5 kg",
      "base_stats": {
        "hp": 54,
        "atk": 66,
        "def": 70,
        "sp_atk": 44,
        "sp_def": 55,
        "speed": 46
      }
    },
    {
      "condition": "Inherited or Random",
      "image_suffix": "super",
      "names": {
        "en": "Super Size",
        "de": "Größe XL"
      },
      "types": [
        "Ghost",
        "Grass"
      ],
      "height_us": "2'07\"",
      "height_eu": "0.8 m",
      "weight_us": "33.1 lbs.",
      "weight_eu": "15.0 kg",
      "base_stats": {
        "hp": 59,
        "atk": 66,
        "def": 70,
        "sp_atk": 44,
        "sp_def": 55,
        "speed": 41
      }
    }
  ],
  "pokedex_entries": {
    "X": {
      "en": "The pumpkin body is inhabited by a spirit trapped in this world. As the sun sets, it becomes restless and active.",
      "de": "Es entsteht aus der Vereinigung einer in der Welt der Lebenden gefangenen Seele mit einem Kürbis. Es wird erst nach Sonnenuntergang aktiv."
    },
    "Y": {
      "en": "It is said to carry wandering spirits to the place where they belong so they can move on.",
      "de": "Man sagt, es führe verlorene Seelen dem Ende ihres rastlosen irdischen Wandelns entgegen und geleite sie sicher ins Jenseits."
    },
    "Omega Ruby": {
      "en": "The pumpkin body is inhabited by a spirit trapped in this world. As the sun sets, it becomes restless and active.",
      "de": "Man sagt, es führe verlorene Seelen dem Ende ihres rastlosen irdischen Wandelns entgegen und geleite sie sicher ins Jenseits."
    },
    "Alpha Sapphire": {
      "en": "It is said to carry wandering spirits to the place where they belong so they can move on.",
      "de": "Man sagt, es führe verlorene Seelen dem Ende ihres rastlosen irdischen Wandelns entgegen und geleite sie sicher ins Jenseits."
    }
  },
  "pokeathlon_stats": {
    "speed": [
      0,
      0
    ],
    "power": [
      0,
      0
    ],
    "stamina": [
      0,
      0
    ],
    "skill": [
      0,
      0
    ],
    "jump": [
      0,
      0
    ]
  },
  "ultra_alola_id": null,
  "move_learnsets": [
    {
      "games": [
        "X",
        "Y"
      ],
      "learnset": [
        {
          "move": "Astonish",
          "level": 1
        },
        {
          "move": "Confuse Ray",
          "level": 1
        },
        {
          "move": "Trick",
          "level": 1
        },
        {
          "move": "Scary Face",
          "level": 4
        },
        {
          "move": "Trick-or-Treat",
          "level": 6
        },
        {
          "move": "Worry Seed",
          "level": 11
        },
        {
          "move": "Razor Leaf",
          "level": 16
        },
        {
          "move": "Leech Seed",
          "level": 20
        },
        {
          "move": "Trick-or-Treat",
          "level": 23
        },
        {
          "move": "Bullet Seed",
          "level": 26
        },
        {
          "move": "Shadow Sneak",
          "level": 30
        },
        {
          "move": "Shadow Ball",
          "level": 36
        },
        {
          "move": "Trick-or-Treat",
          "level": 40
        },
        {
          "move": "Pain Split",
          "level": 42
        },
        {
          "move": "Seed Bomb",
          "level": 48
        },
        {
          "move": "Bestow",
          "egg_move": true
        },
        {
          "move": "Destiny Bond",
          "egg_move": true
        },
        {
          "move": "Disable",
          "egg_move": true
        },
        {
          "move": "Toxic",
          "tm": "TM6"
        },
        {
          "move": "Hidden Power",
          "tm": "TM10"
        },
        {
          "move": "Sunny Day",
          "tm": "TM11"
        },
        {
          "move": "Light Screen",
          "tm": "TM16"
        },
        {
          "move": "Protect",
          "tm": "TM17"
        },
        {
          "move": "Safeguard",
          "tm": "TM20"
        },
        {
          "move": "Frustration",
          "tm": "TM21"
        },
        {
          "move": "Solar Beam",
          "tm": "TM22"
        },
        {
          "move": "Return",
          "tm": "TM27"
        },
        {
          "move": "Psychic",
          "tm": "TM29"
        },
        {
          "move": "Shadow Ball",
          "tm": "TM30"
        },
        {
          "move": "Double Team",
          "tm": "TM32"
        },
        {
          "move": "Flamethrower",
          "tm": "TM35"
        },
        {
          "move": "Sludge Bomb",
          "tm": "TM36"
        },
        {
          "move": "Fire Blast",
          "tm": "TM38"
        },
        {
          "move": "Facade",
          "tm": "TM42"
        },
        {
          "move": "Flame Charge",
          "tm": "TM43"
        },
        {
          "move": "Rest",
          "tm": "TM44"
        },
        {
          "move": "Attract",
          "tm": "TM45"
        },
        {
          "move": "Thief",
          "tm": "TM46"
        },
        {
          "move": "Round",
          "tm": "TM48"
        },
        {
          "move": "Energy Ball",
          "tm": "TM53"
        },
        {
          "move": "Charge Beam",
          "tm": "TM57"
        },
        {
          "move": "Incinerate",
          "tm": "TM59"
        },
        {
          "move": "Will-O-Wisp",
          "tm": "TM61"
        },
        {
          "move": "Explosion",
          "tm": "TM64"
        },
        {
          "move": "Flash",
          "tm": "TM70"
        },
        {
          "move": "Gyro Ball",
          "tm": "TM74"
        },
        {
          "move": "Rock Slide",
          "tm": "TM80"
        },
        {
          "move": "Dream Eater",
          "tm": "TM85"
        },
        {
          "move": "Grass Knot",
          "tm": "TM86"
        },
        {
          "move": "Swagger",
          "tm": "TM87"
        },
        {
          "move": "Sleep Talk",
          "tm": "TM88"
        },
        {
          "move": "Substitute",
          "tm": "TM90"
        },
        {
          "move": "Trick Room",
          "tm": "TM92"
        },
        {
          "move": "Rock Smash",
          "tm": "TM94"
        },
        {
          "move": "Nature Power",
          "tm": "TM96"
        },
        {
          "move": "Dark Pulse",
          "tm": "TM97"
        },
        {
          "move": "Confide",
          "tm": "TM100"
        }
      ]
    },
    {
      "games": [
        "Omega Ruby",
        "Alpha Sapphire"
      ],
      "learnset": [
        {
          "move": "Astonish",
          "level": 1
        },
        {
          "move": "Confuse Ray",
          "level": 1
        },
        {
          "move": "Trick",
          "level": 1
        },
        {
          "move": "Scary Face",
          "level": 4
        },
        {
          "move": "Trick-or-Treat",
          "level": 6
        },
        {
          "move": "Worry Seed",
          "level": 11
        },
        {
          "move": "Razor Leaf",
          "level": 16
        },
        {
          "move": "Leech Seed",
          "level": 20
        },
        {
          "move": "Trick-or-Treat",
          "level": 23
        },
        {
          "move": "Bullet Seed",
          "level": 26
        },
        {
          "move": "Shadow Sneak",
          "level": 30
        },
        {
          "move": "Shadow Ball",
          "level": 36
        },
        {
          "move": "Trick-or-Treat",
          "level": 40
        },
        {
          "move": "Pain Split",
          "level": 42
        },
        {
          "move": "Seed Bomb",
          "level": 48
        },
        {
          "move": "Bestow",
          "egg_move": true
        },
        {
          "move": "Destiny Bond",
          "egg_move": true
        },
        {
          "move": "Disable",
          "egg_move": true
        },
        {
          "move": "Rock Smash",
          "tm": "HM6"
        },
        {
          "move": "Toxic",
          "tm": "TM6"
        },
        {
          "move": "Hidden Power",
          "tm": "TM10"
        },
        {
          "move": "Sunny Day",
          "tm": "TM11"
        },
        {
          "move": "Light Screen",
          "tm": "TM16"
        },
        {
          "move": "Protect",
          "tm": "TM17"
        },
        {
          "move": "Safeguard",
          "tm": "TM20"
        },
        {
          "move": "Frustration",
          "tm": "TM21"
        },
        {
          "move": "Solar Beam",
          "tm": "TM22"
        },
        {
          "move": "Return",
          "tm": "TM27"
        },
        {
          "move": "Psychic",
          "tm": "TM29"
        },
        {
          "move": "Shadow Ball",
          "tm": "TM30"
        },
        {
          "move": "Double Team",
          "tm": "TM32"
        },
        {
          "move": "Flamethrower",
          "tm": "TM35"
        },
        {
          "move": "Sludge Bomb",
          "tm": "TM36"
        },
        {
          "move": "Fire Blast",
          "tm": "TM38"
        },
        {
          "move": "Facade",
          "tm": "TM42"
        },
        {
          "move": "Flame Charge",
          "tm": "TM43"
        },
        {
          "move": "Rest",
          "tm": "TM44"
        },
        {
          "move": "Attract",
          "tm": "TM45"
        },
        {
          "move": "Thief",
          "tm": "TM46"
        },
        {
          "move": "Round",
          "tm": "TM48"
        },
        {
          "move": "Energy Ball",
          "tm": "TM53"
        },
        {
          "move": "Charge Beam",
          "tm": "TM57"
        },
        {
          "move": "Incinerate",
          "tm": "TM59"
        },
        {
          "move": "Will-O-Wisp",
          "tm": "TM61"
        },
        {
          "move": "Explosion",
          "tm": "TM64"
        },
        {
          "move": "Flash",
          "tm": "TM70"
        },
        {
          "move": "Gyro Ball",
          "tm": "TM74"
        },
        {
          "move": "Rock Slide",
          "tm": "TM80"
        },
        {
          "move": "Dream Eater",
          "tm": "TM85"
        },
        {
          "move": "Grass Knot",
          "tm": "TM86"
        },
        {
          "move": "Swagger",
          "tm": "TM87"
        },
        {
          "move": "Sleep Talk",
          "tm": "TM88"
        },
        {
          "move": "Substitute",
          "tm": "TM90"
        },
        {
          "move": "Trick Room",
          "tm": "TM92"
        },
        {
          "move": "Secret Power",
          "tm": "TM94"
        },
        {
          "move": "Nature Power",
          "tm": "TM96"
        },
        {
          "move": "Dark Pulse",
          "tm": "TM97"
        },
        {
          "move": "Confide",
          "tm": "TM100"
        }
      ]
    },
    {
      "games": [
        "Sun",
        "Moon"
      ],
      "learnset": [
        {
          "move": "Astonish",
          "level": 1
        },
        {
          "move": "Confuse Ray",
          "level": 1
        },
        {
          "move": "Trick",
          "level": 1
        },
        {
          "move": "Scary Face",
          "level": 4
        },
        {
          "move": "Trick-or-Treat",
          "level": 6
        },
        {
          "move": "Worry Seed",
          "level": 11
        },
        {
          "move": "Razor Leaf",
          "level": 16
        },
        {
          "move": "Leech Seed",
          "level": 20
        },
        {
          "move": "Trick-or-Treat",
          "level": 23
        },
        {
          "move": "Bullet Seed",
          "level": 26
        },
        {
          "move": "Shadow Sneak",
          "level": 30
        },
        {
          "move": "Shadow Ball",
          "level": 36
        },
        {
          "move": "Trick-or-Treat",
          "level": 40
        },
        {
          "move": "Pain Split",
          "level": 42
        },
        {
          "move": "Seed Bomb",
          "level": 48
        },
        {
          "move": "Bestow",
          "egg_move": true
        },
        {
          "move": "Destiny Bond",
          "egg_move": true
        },
        {
          "move": "Disable",
          "egg_move": true
        },
        {
          "move": "Toxic",
          "tm": "TM6"
        },
        {
          "move": "Hidden Power",
          "tm": "TM10"
        },
        {
          "move": "Sunny Day",
          "tm": "TM11"
        },
        {
          "move": "Light Screen",
          "tm": "TM16"
        },
        {
          "move": "Protect",
          "tm": "TM17"
        },
        {
          "move": "Safeguard",
          "tm": "TM20"
        },
        {
          "move": "Frustration",
          "tm": "TM21"
        },
        {
          "move": "Solar Beam",
          "tm": "TM22"
        },
        {
          "move": "Return",
          "tm": "TM27"
        },
        {
          "move": "Psychic",
          "tm": "TM29"
        },
        {
          "move": "Shadow Ball",
          "tm": "TM30"
        },
        {
          "move": "Double Team",
          "tm": "TM32"
        },
        {
          "move": "Flamethrower",
          "tm": "TM35"
        },
        {
          "move": "Sludge Bomb",
          "tm": "TM36"
        },
        {
          "move": "Fire Blast",
          "tm": "TM38"
        },
        {
          "move": "Facade",
          "tm": "TM42"
        },
        {
          "move": "Flame Charge",
          "tm": "TM43"
        },
        {
          "move": "Rest",
          "tm": "TM44"
        },
        {
          "move": "Attract",
          "tm": "TM45"
        },
        {
          "move": "Thief",
          "tm": "TM46"
        },
        {
          "move": "Round",
          "tm": "TM48"
        },
        {
          "move": "Energy Ball",
          "tm": "TM53"
        },
        {
          "move": "Charge Beam",
          "tm": "TM57"
        },
        {
          "move": "Will-O-Wisp",
          "tm": "TM61"
        },
        {
          "move": "Explosion",
          "tm": "TM64"
        },
        {
          "move": "Gyro Ball",
          "tm": "TM74"
        },
        {
          "move": "Rock Slide",
          "tm": "TM80"
        },
        {
          "move": "Dream Eater",
          "tm": "TM85"
        },
        {
          "move": "Grass Knot",
          "tm": "TM86"
        },
        {
          "move": "Swagger",
          "tm": "TM87"
        },
        {
          "move": "Sleep Talk",
          "tm": "TM88"
        },
        {
          "move": "Substitute",
          "tm": "TM90"
        },
        {
          "move": "Trick Room",
          "tm": "TM92"
        },
        {
          "move": "Nature Power",
          "tm": "TM96"
        },
        {
          "move": "Dark Pulse",
          "tm": "TM97"
        },
        {
          "move": "Confide",
          "tm": "TM100"
        }
      ]
    },
    {
      "games": [
        "Ultra Sun",
        "Ultra Moon"
      ],
      "learnset": [
        {
          "move": "Astonish",
          "level": 1
        },
        {
          "move": "Confuse Ray",
          "level": 1
        },
        {
          "move": "Trick",
          "level": 1
        },
        {
          "move": "Scary Face",
          "level": 4
        },
        {
          "move": "Trick-or-Treat",
          "level": 6
        },
        {
          "move": "Worry Seed",
          "level": 11
        },
        {
          "move": "Razor Leaf",
          "level": 16
        },
        {
          "move": "Leech Seed",
          "level": 20
        },
        {
          "move": "Trick-or-Treat",
          "level": 23
        },
        {
          "move": "Bullet Seed",
          "level": 26
        },
        {
          "move": "Shadow Sneak",
          "level": 30
        },
        {
          "move": "Shadow Ball",
          "level": 36
        },
        {
          "move": "Trick-or-Treat",
          "level": 40
        },
        {
          "move": "Pain Split",
          "level": 42
        },
        {
          "move": "Seed Bomb",
          "level": 48
        },
        {
          "move": "Bestow",
          "egg_move": true
        },
        {
          "move": "Curse",
          "egg_move": true
        },
        {
          "move": "Destiny Bond",
          "egg_move": true
        },
        {
          "move": "Disable",
          "egg_move": true
        },
        {
          "move": "Toxic",
          "tm": "TM6"
        },
        {
          "move": "Hidden Power",
          "tm": "TM10"
        },
        {
          "move": "Sunny Day",
          "tm": "TM11"
        },
        {
          "move": "Light Screen",
          "tm": "TM16"
        },
        {
          "move": "Protect",
          "tm": "TM17"
        },
        {
          "move": "Safeguard",
          "tm": "TM20"
        },
        {
          "move": "Frustration",
          "tm": "TM21"
        },
        {
          "move": "Solar Beam",
          "tm": "TM22"
        },
        {
          "move": "Return",
          "tm": "TM27"
        },
        {
          "move": "Psychic",
          "tm": "TM29"
        },
        {
          "move": "Shadow Ball",
          "tm": "TM30"
        },
        {
          "move": "Double Team",
          "tm": "TM32"
        },
        {
          "move": "Flamethrower",
          "tm": "TM35"
        },
        {
          "move": "Sludge Bomb",
          "tm": "TM36"
        },
        {
          "move": "Fire Blast",
          "tm": "TM38"
        },
        {
          "move": "Facade",
          "tm": "TM42"
        },
        {
          "move": "Flame Charge",
          "tm": "TM43"
        },
        {
          "move": "Rest",
          "tm": "TM44"
        },
        {
          "move": "Attract",
          "tm": "TM45"
        },
        {
          "move": "Thief",
          "tm": "TM46"
        },
        {
          "move": "Round",
          "tm": "TM48"
        },
        {
          "move": "Energy Ball",
          "tm": "TM53"
        },
        {
          "move": "Charge Beam",
          "tm": "TM57"
        },
        {
          "move": "Will-O-Wisp",
          "tm": "TM61"
        },
        {
          "move": "Explosion",
          "tm": "TM64"
        },
        {
          "move": "Gyro Ball",
          "tm": "TM74"
        },
        {
          "move": "Rock Slide",
          "tm": "TM80"
        },
        {
          "move": "Dream Eater",
          "tm": "TM85"
        },
        {
          "move": "Grass Knot",
          "tm": "TM86"
        },
        {
          "move": "Swagger",
          "tm": "TM87"
        },
        {
          "move": "Sleep Talk",
          "tm": "TM88"
        },
        {
          "move": "Substitute",
          "tm": "TM90"
        },
        {
          "move": "Trick Room",
          "tm": "TM92"
        },
        {
          "move": "Nature Power",
          "tm": "TM96"
        },
        {
          "move": "Dark Pulse",
          "tm": "TM97"
        },
        {
          "move": "Confide",
          "tm": "TM100"
        }
      ]
    }
  ]
}