{
  "names": {
    "fr": "Togetic",
    "de": "Togetic",
    "it": "Togetic",
    "en": "Togetic"
  },
  "national_id": 176,
  "types": [
    "Fairy",
    "Flying"
  ],
  "abilities": [
    {
      "name": "Hustle"
    },
    {
      "name": "Super Luck",
      "hidden": true
    }
  ],
  "gender_ratios": {
    "male": 87.5,
    "female": 12.5
  },
  "catch_rate": 75,
  "egg_groups": [
    "Flying",
    "Fairy"
  ],
  "hatch_time": [
    2805,
    3059
  ],
  "height_us": "2'00\"",
  "height_eu": "0.6 m",
  "weight_us": "7.1 lbs.",
  "weight_eu": "3.2 kg",
  "base_exp_yield": 142,
  "leveling_rate": "Fast",
  "ev_yield": {
    "hp": 0,
    "atk": 0,
    "def": 0,
    "sp_atk": 0,
    "sp_def": 2,
    "speed": 0
  },
  "color": "White",
  "base_friendship": 70,
  "base_stats": {
    "hp": 55,
    "atk": 40,
    "def": 85,
    "sp_atk": 80,
    "sp_def": 105,
    "speed": 40
  },
  "learnset": [
    {
      "level": 0,
      "move": "Magical Leaf"
    },
    {
      "level": 0,
      "move": "Growl"
    },
    {
      "level": 0,
      "move": "Charm"
    },
    {
      "level": 0,
      "move": "Metronome"
    },
    {
      "level": 0,
      "move": "Sweet Kiss"
    },
    {
      "level": 5,
      "move": "Metronome"
    },
    {
      "level": 9,
      "move": "Sweet Kiss"
    },
    {
      "level": 13,
      "move": "Yawn"
    },
    {
      "level": 14,
      "move": "Fairy Wind"
    },
    {
      "level": 17,
      "move": "Encore"
    },
    {
      "level": 21,
      "move": "Follow Me"
    },
    {
      "level": 25,
      "move": "Bestow"
    },
    {
      "level": 29,
      "move": "Wish"
    },
    {
      "level": 33,
      "move": "Ancient Power"
    },
    {
      "level": 37,
      "move": "Safeguard"
    },
    {
      "level": 41,
      "move": "Baton Pass"
    },
    {
      "level": 45,
      "move": "Double-Edge"
    },
    {
      "level": 49,
      "move": "Last Resort"
    },
    {
      "level": 53,
      "move": "After You"
    },
    {
      "tm": "TM03",
      "move": "Psyshock"
    },
    {
      "tm": "TM06",
      "move": "Toxic"
    },
    {
      "tm": "TM10",
      "move": "Hidden Power"
    },
    {
      "tm": "TM11",
      "move": "Sunny Day"
    },
    {
      "tm": "TM15",
      "move": "Hyper Beam"
    },
    {
      "tm": "TM16",
      "move": "Light Screen"
    },
    {
      "tm": "TM17",
      "move": "Protect"
    },
    {
      "tm": "TM18",
      "move": "Rain Dance"
    },
    {
      "tm": "TM19",
      "move": "Roost"
    },
    {
      "tm": "TM20",
      "move": "Safeguard"
    },
    {
      "tm": "TM21",
      "move": "Frustration"
    },
    {
      "tm": "TM22",
      "move": "Solar Beam"
    },
    {
      "tm": "TM27",
      "move": "Return"
    },
    {
      "tm": "TM29",
      "move": "Psychic"
    },
    {
      "tm": "TM30",
      "move": "Shadow Ball"
    },
    {
      "tm": "TM31",
      "move": "Brick Break"
    },
    {
      "tm": "TM32",
      "move": "Double Team"
    },
    {
      "tm": "TM33",
      "move": "Reflect"
    },
    {
      "tm": "TM35",
      "move": "Flamethrower"
    },
    {
      "tm": "TM38",
      "move": "Fire Blast"
    },
    {
      "tm": "TM40",
      "move": "Aerial Ace"
    },
    {
      "tm": "TM42",
      "move": "Facade"
    },
    {
      "tm": "TM44",
      "move": "Rest"
    },
    {
      "tm": "TM45",
      "move": "Attract"
    },
    {
      "tm": "TM48",
      "move": "Round"
    },
    {
      "tm": "TM49",
      "move": "Echoed Voice"
    },
    {
      "tm": "TM51",
      "move": "Steel Wing"
    },
    {
      "tm": "TM56",
      "move": "Fling"
    },
    {
      "tm": "TM59",
      "move": "Incinerate"
    },
    {
      "tm": "TM67",
      "move": "Retaliate"
    },
    {
      "tm": "TM68",
      "move": "Giga Impact"
    },
    {
      "tm": "TM70",
      "move": "Flash"
    },
    {
      "tm": "TM73",
      "move": "Thunder Wave"
    },
    {
      "tm": "TM77",
      "move": "Psych Up"
    },
    {
      "tm": "TM85",
      "move": "Dream Eater"
    },
    {
      "tm": "TM86",
      "move": "Grass Knot"
    },
    {
      "tm": "TM87",
      "move": "Swagger"
    },
    {
      "tm": "TM88",
      "move": "Sleep Talk"
    },
    {
      "tm": "TM90",
      "move": "Substitute"
    },
    {
      "tm": "TM94",
      "move": "Rock Smash"
    },
    {
      "tm": "TM94",
      "move": "Secret Power"
    },
    {
      "tm": "TM99",
      "move": "Dazzling Gleam"
    },
    {
      "tm": "TM100",
      "move": "Confide"
    },
    {
      "tm": "HM02",
      "move": "Fly"
    },
    {
      "tm": "HM06",
      "move": "Rock Smash"
    },
    {
      "parent": "Hoothoot",
      "move": "Extrasensory"
    },
    {
      "parent": "Noctowl",
      "move": "Extrasensory"
    },
    {
      "parent": "Hoothoot",
      "move": "Foresight"
    },
    {
      "parent": "Noctowl",
      "move": "Foresight"
    },
    {
      "parent": "Skitty",
      "move": "Foresight"
    },
    {
      "parent": "Natu",
      "move": "Future Sight"
    },
    {
      "parent": "Xatu",
      "move": "Future Sight"
    },
    {
      "parent": "Woobat",
      "move": "Future Sight"
    },
    {
      "parent": "Swoobat",
      "move": "Future Sight"
    },
    {
      "parent": "Clefairy",
      "move": "Lucky Chant"
    },
    {
      "parent": "Clefable",
      "move": "Lucky Chant"
    },
    {
      "parent": "Natu",
      "move": "Lucky Chant"
    },
    {
      "parent": "Xatu",
      "move": "Lucky Chant"
    },
    {
      "parent": "Cherubi",
      "move": "Lucky Chant"
    },
    {
      "parent": "Cherrim",
      "move": "Lucky Chant"
    },
    {
      "parent": "Pidgey",
      "move": "Mirror Move"
    },
    {
      "parent": "Pidgeotto",
      "move": "Mirror Move"
    },
    {
      "parent": "Pidgeot",
      "move": "Mirror Move"
    },
    {
      "parent": "Spearow",
      "move": "Mirror Move"
    },
    {
      "parent": "Fearow",
      "move": "Mirror Move"
    },
    {
      "parent": "Swablu",
      "move": "Mirror Move"
    },
    {
      "parent": "Altaria",
      "move": "Mirror Move"
    },
    {
      "parent": "Chatot",
      "move": "Mirror Move"
    },
    {
      "parent": "Sigilyph",
      "move": "Mirror Move"
    },
    {
      "parent": "Cherubi",
      "move": "Morning Sun"
    },
    {
      "parent": "Cherrim",
      "move": "Morning Sun"
    },
    {
      "parent": "Plusle",
      "move": "Nasty Plot"
    },
    {
      "parent": "Minun",
      "move": "Nasty Plot"
    },
    {
      "parent": "Honchkrow",
      "move": "Nasty Plot"
    },
    {
      "parent": "Spearow",
      "move": "Peck"
    },
    {
      "parent": "Fearow",
      "move": "Peck"
    },
    {
      "parent": "Farfetch'd",
      "move": "Peck"
    },
    {
      "parent": "Doduo",
      "move": "Peck"
    },
    {
      "parent": "Dodrio",
      "move": "Peck"
    },
    {
      "parent": "Hoothoot",
      "move": "Peck"
    },
    {
      "parent": "Noctowl",
      "move": "Peck"
    },
    {
      "parent": "Natu",
      "move": "Peck"
    },
    {
      "parent": "Xatu",
      "move": "Peck"
    },
    {
      "parent": "Murkrow",
      "move": "Peck"
    },
    {
      "parent": "Honchkrow",
      "move": "Peck"
    },
    {
      "parent": "Skarmory",
      "move": "Peck"
    },
    {
      "parent": "Taillow",
      "move": "Peck"
    },
    {
      "parent": "Swellow",
      "move": "Peck"
    },
    {
      "parent": "Swablu",
      "move": "Peck"
    },
    {
      "parent": "Altaria",
      "move": "Peck"
    },
    {
      "parent": "Chatot",
      "move": "Peck"
    },
    {
      "parent": "Rufflet",
      "move": "Peck"
    },
    {
      "parent": "Braviary",
      "move": "Peck"
    },
    {
      "parent": "Fletchling",
      "move": "Peck"
    },
    {
      "parent": "Fletchinder",
      "move": "Peck"
    },
    {
      "parent": "Talonflame",
      "move": "Peck"
    },
    {
      "parent": "Pikachu",
      "move": "Present"
    },
    {
      "parent": "Marill",
      "move": "Present"
    },
    {
      "parent": "Snubbull",
      "move": "Present"
    },
    {
      "parent": "Hoothoot",
      "move": "Psycho Shift"
    },
    {
      "parent": "Noctowl",
      "move": "Psycho Shift"
    },
    {
      "parent": "Natu",
      "move": "Psycho Shift"
    },
    {
      "parent": "Xatu",
      "move": "Psycho Shift"
    },
    {
      "parent": "Audino",
      "move": "Secret Power"
    },
    {
      "parent": "Clefairy",
      "move": "Stored Power"
    },
    {
      "parent": "Natu",
      "move": "Stored Power"
    },
    {
      "parent": "Xatu",
      "move": "Stored Power"
    }
  ],
  "evolutions": [
    {
      "to": "Togekiss",
      "item": "Shiny Stone"
    }
  ],
  "evolution_from": "Togepi",
  "categories": {
    "en": "Happiness Pokémon",
    "de": "Freude"
  },
  "kanto_id": null,
  "johto_id": 47,
  "hoenn_id": null,
  "sinnoh_id": 174,
  "unova_id": null,
  "kalos_id": null,
  "alola_id": null,
  "mega_evolutions": [

  ],
  "variations": [

  ],
  "pokedex_entries": {
    "Gold": {
      "en": "They say that it will appear before kindhearted, caring people and shower them with happiness.",
      "de": "Man sagt, es zeigt sich nur gutherzigen und einfühlsamen Menschen. Es überschüttet sie mit Freude."
    },
    "Silver": {
      "en": "It grows dispirited if it is not with kind people. It can float in midair without moving its wings.",
      "de": "Es wird entmutigt, wenn es unter unfreundlichen Menschen ist. Es kann ohne Flügel niedrig schweben."
    },
    "Crystal": {
      "en": "Although it does not flap its wings very much, it can stay up in the air as it tags along after its trainer.",
      "de": "Obwohl es nicht mit den Flügeln schlägt, hält es sich in der Luft, wenn es seinem Trainer folgt."
    },
    "Ruby": {
      "en": "Togetic is said to be a Pokémon that brings good fortune. When the Pokémon spots someone who is pure of heart, it is said to appear and share its happiness with that person.",
      "de": "Togetic ist ein Pokémon, das Glück bringt. Wenn es jemanden trifft, der reinen Herzens ist, zeigt es sich und teilt sein Glück mit dieser Person."
    },
    "Sapphire": {
      "en": "Togetic is said to be a Pokémon that brings good fortune. When the Pokémon spots someone who is pure of heart, it is said to appear and share its happiness with that person.",
      "de": "Togetic ist ein Pokémon, das Glück bringt. Wenn es jemanden trifft, der gutherzig ist, teilt es seine Freude mit dieser Person."
    },
    "Emerald": {
      "en": "It is said to be a Pokémon that brings good fortune. When it spots someone who is pure of heart, a Togetic appears and shares its happiness with that person.",
      "de": "TOGETIC ist ein POKÉMON, das Glück bringt. Wenn es jemanden trifft, der reinen Herzens ist, zeigt es sich und teilt sein Glück mit dieser Person."
    },
    "FireRed": {
      "en": "It grows dispirited if it is not with kind people. It can float in midair without moving its wings.",
      "de": "Es wird entmutigt, wenn es unter unfreundlichen Menschen ist. Es kann ohne Flügel niedrig schweben."
    },
    "LeafGreen": {
      "en": "They say that it will appear before kindhearted, caring people and shower them with happiness.",
      "de": "Man sagt, es zeigt sich nur gutherzigen und einfühlsamen Menschen. Es überschüttet sie mit Freude."
    },
    "Diamond": {
      "en": "It is said to appear in front of kindly people to scatter a glowing down called \"joy dust.\"",
      "de": "Man sagt, es erscheint vor denen, die gutherzig sind, und verteilt glänzenden “Glücksstaub”."
    },
    "Pearl": {
      "en": "It is said to appear in front of kindly people to scatter a glowing down called \"joy dust.\"",
      "de": "Man sagt, es erscheint vor denen, die gutherzig sind, und verteilt glänzenden “Glücksstaub”."
    },
    "Platinum": {
      "en": "To share its happiness, it flies around the world seeking kind-hearted people.",
      "de": "Um sein Glück mit anderen zu teilen , fliegt es um die Welt auf der Suche nach gutherzigen Menschen."
    },
    "HeartGold": {
      "en": "They say that it will appear before kindhearted, caring people and shower them with happiness.",
      "de": "Man sagt, es erscheint vor denen, die gutherzig sind, und verteilt glänzenden “Glücksstaub”."
    },
    "SoulSilver": {
      "en": "It grows dispirited if it is not with kind people. It can float in midair without moving its wings.",
      "de": "Man sagt, es erscheint vor denen, die gutherzig sind, und verteilt glänzenden “Glücksstaub”."
    },
    "Black": {
      "en": "To share its happiness, it flies around the world seeking kind-hearted people.",
      "de": "Um sein Glück mit anderen zu teilen, fliegt es um die Welt auf der Suche nach gutherzigen Menschen."
    },
    "White": {
      "en": "To share its happiness, it flies around the world seeking kind-hearted people.",
      "de": "Um sein Glück mit anderen zu teilen, fliegt es um die Welt auf der Suche nach gutherzigen Menschen."
    },
    "Black 2": {
      "en": "To share its happiness, it flies around the world seeking kind-hearted people.",
      "de": "Um sein Glück mit anderen zu teilen, fliegt es um die Welt auf der Suche nach gutherzigen Menschen."
    },
    "White 2": {
      "en": "To share its happiness, it flies around the world seeking kind-hearted people.",
      "de": "Um sein Glück mit anderen zu teilen, fliegt es um die Welt auf der Suche nach gutherzigen Menschen."
    },
    "X": {
      "en": "It grows dispirited if it is not with kind people. It can float in midair without moving its wings.",
      "de": "Es wird entmutigt, wenn es unter unfreundlichen Menschen ist. Es kann ohne Flügel niedrig schweben."
    },
    "Y": {
      "en": "They say that it will appear before kindhearted, caring people and shower them with happiness.",
      "de": "Man sagt, es zeigt sich nur gutherzigen und einfühlsamen Menschen. Es überschüttet sie mit Freude."
    },
    "Omega Ruby": {
      "en": "Togetic is said to be a Pokémon that brings good fortune. When the Pokémon spots someone who is pure of heart, it is said to appear and share its happiness with that person.",
      "de": "Togetic ist ein Pokémon, das Glück bringt. Wenn es jemanden trifft, der gutherzig ist, teilt es seine Freude mit dieser Person."
    },
    "Alpha Sapphire": {
      "en": "Togetic is said to be a Pokémon that brings good fortune. When the Pokémon spots someone who is pure of heart, it is said to appear and share its happiness with that person.",
      "de": "Togetic ist ein Pokémon, das Glück bringt. Wenn es jemanden trifft, der gutherzig ist, teilt es seine Freude mit dieser Person."
    }
  },
  "pokeathlon_stats": {
    "speed": [
      3,
      4
    ],
    "power": [
      2,
      5
    ],
    "stamina": [
      4,
      5
    ],
    "skill": [
      3,
      3
    ],
    "jump": [
      4,
      5
    ]
  }
}