{
  "names": {
    "en": "Malicious Moonsault",
    "fr": "Dark Body Press",
    "de": "Hyper Dark Crusher",
    "it": "Iperschianto delle Tenebre",
    "es": "Hiperplancha Oscura"
  },
  "index_number": 696,
  "makes_contact": false,
  "affected_by_protect": false,
  "affected_by_magic_coat": false,
  "affected_by_snatch": false,
  "affected_by_mirror_move": false,
  "affected_by_kings_rock": true,
  "type": "Dark",
  "category": "physical",
  "pp": 0,
  "max_pp": 0,
  "power": 180,
  "accuracy": 0,
  "target": "target_adjacent_single",
  "critical_hit": 0,
  "priority": 0,
  "contests": [

  ],
  "pokedex_entries": {
    "Sun": {
      "en": "The user, Incineroar, strengthens its body using its Z-Power and crashes into the target with full force.",
      "de": "Mit seinem durch Z-Kraft gestählten Körper stürzt sich Fuegro mit ganzer Kraft auf das Ziel."
    },
    "Moon": {
      "en": "The user, Incineroar, strengthens its body using its Z-Power and crashes into the target with full force.",
      "de": "Mit seinem durch Z-Kraft gestählten Körper stürzt sich Fuegro mit ganzer Kraft auf das Ziel."
    },
    "Ultra Sun": {
      "en": "The user, Incineroar, strengthens its body using its Z-Power and crashes into the target with full force.",
      "de": "Mit seinem durch Z-Kraft gestählten Körper stürzt sich Fuegro mit ganzer Kraft auf das Ziel."
    },
    "Ultra Moon": {
      "en": "The user, Incineroar, strengthens its body using its Z-Power and crashes into the target with full force.",
      "de": "Mit seinem durch Z-Kraft gestählten Körper stürzt sich Fuegro mit ganzer Kraft auf das Ziel."
    }
  }
}