{
  "index_number": 276,
  "pp": 5,
  "max_pp": 8,
  "power": 120,
  "accuracy": 100,
  "category": "physical",
  "priority": 0,
  "target": "target_adjacent_single",
  "critical_hit": 0,
  "makes_contact": true,
  "affected_by_protect": true,
  "affected_by_magic_coat": false,
  "affected_by_snatch": false,
  "affected_by_mirror_move": false,
  "affected_by_kings_rock": false,
  "names": {
    "fr": "Surpuissance",
    "de": "Kraftkoloss",
    "gr": "Υπερδύναμη",
    "it": "Troppoforte",
    "pl": "Super Moc",
    "en": "Superpower"
  },
  "type": "Fighting",
  "contests": [
    {
      "contest": "Contests",
      "appeal": 6,
      "jam": 0,
      "condition": "Tough"
    },
    {
      "contest": "Super Contests",
      "appeal": 2,
      "jam": 0,
      "condition": "Tough"
    },
    {
      "contest": "Contest Spectaculars",
      "appeal": 6,
      "jam": 0,
      "condition": "Tough"
    }
  ],
  "stat_modifiers": [
    {
      "stat": "atk",
      "change_by": -1,
      "affects_user": true
    },
    {
      "stat": "def",
      "change_by": -1,
      "affects_user": true
    }
  ],
  "pokedex_entries": {
    "Ruby": {
      "en": "Boosts strength sharply, but lowers abilities.",
      "de": "Steigert Stärke deutlich, senkt aber Statuswerte."
    },
    "Sapphire": {
      "en": "Boosts strength sharply, but lowers abilities.",
      "de": "Steigert Stärke deutlich, senkt aber Statuswerte."
    },
    "Emerald": {
      "en": "Boosts strength sharply, but lowers abilities.",
      "de": "Steigert Stärke deutlich, senkt aber Statuswerte."
    },
    "FireRed": {
      "en": "A powerful attack, but it also lowers the user’s ATTACK and DEFENSE stats.",
      "de": "Starker Angriff, der sowohl ANGR. als auch VERT. des Anwenders senkt."
    },
    "LeafGreen": {
      "en": "A powerful attack, but it also lowers the user’s ATTACK and DEFENSE stats.",
      "de": "Starker Angriff, der sowohl ANGR. als auch VERT. des Anwenders senkt."
    },
    "Diamond": {
      "en": "The user attacks the foe with great power. However, it also lowers the user’s Attack and Defense.",
      "de": "Starker Angriff, der sowohl Angriff als auch Verteidigung des Anwenders senkt."
    },
    "Pearl": {
      "en": "The user attacks the foe with great power. However, it also lowers the user’s Attack and Defense.",
      "de": "Starker Angriff, der sowohl Angriff als auch Verteidigung des Anwenders senkt."
    },
    "Platinum": {
      "en": "The user attacks the foe with great power. However, it also lowers the user’s Attack and Defense.",
      "de": "Starker Angriff, der sowohl Angriff als auch Verteidigung des Anwenders senkt."
    },
    "HeartGold": {
      "en": "The user attacks the foe with great power. However, it also lowers the user’s Attack and Defense.",
      "de": "Starker Angriff, der sowohl Angriff als auch Verteidigung des Anwenders senkt."
    },
    "SoulSilver": {
      "en": "The user attacks the foe with great power. However, it also lowers the user’s Attack and Defense.",
      "de": "Starker Angriff, der sowohl Angriff als auch Verteidigung des Anwenders senkt."
    },
    "Black": {
      "en": "The user attacks the target with great power. However, it also lowers the user’s Attack and Defense.",
      "de": "Starke Attacke, die sowohl Angriff als auch Verteidigung des Anwenders senkt."
    },
    "White": {
      "en": "The user attacks the target with great power. However, it also lowers the user’s Attack and Defense.",
      "de": "Starke Attacke, die sowohl Angriff als auch Verteidigung des Anwenders senkt."
    },
    "Black 2": {
      "en": "The user attacks the target with great power. However, it also lowers the user’s Attack and Defense.",
      "de": "Starke Attacke, die sowohl Angriff als auch Verteidigung des Anwenders senkt."
    },
    "White 2": {
      "en": "The user attacks the target with great power. However, it also lowers the user’s Attack and Defense.",
      "de": "Starke Attacke, die sowohl Angriff als auch Verteidigung des Anwenders senkt."
    },
    "X": {
      "en": "The user attacks the target with great power. However, this also lowers the user’s Attack and Defense stats.",
      "de": "Starke Attacke, die jedoch auch den Angriff und die Verteidigung des Anwenders senkt."
    },
    "Y": {
      "en": "The user attacks the target with great power. However, this also lowers the user’s Attack and Defense stats.",
      "de": "Starke Attacke, die jedoch auch den Angriff und die Verteidigung des Anwenders senkt."
    },
    "O.Ruby": {
      "en": "The user attacks the target with great power. However, this also lowers the user’s Attack and Defense stats.",
      "de": "Unbekannt"
    },
    "A.Sapphire": {
      "en": "The user attacks the target with great power. However, this also lowers the user’s Attack and Defense stats.",
      "de": "Unbekannt"
    },
    "Sun": {
      "en": "The user attacks the target with great power. However, this also lowers the user’s Attack and Defense stats.",
      "de": "Starke Attacke, die jedoch auch den Angriff und die Verteidigung des Anwenders senkt."
    },
    "Moon": {
      "en": "The user attacks the target with great power. However, this also lowers the user’s Attack and Defense stats.",
      "de": "Starke Attacke, die jedoch auch den Angriff und die Verteidigung des Anwenders senkt."
    },
    "Ultra Sun": {
      "en": "The user attacks the target with great power. However, this also lowers the user’s Attack and Defense stats.",
      "de": "Starke Attacke, die jedoch auch den Angriff und die Verteidigung des Anwenders senkt."
    },
    "Ultra Moon": {
      "en": "The user attacks the target with great power. However, this also lowers the user’s Attack and Defense stats.",
      "de": "Starke Attacke, die jedoch auch den Angriff und die Verteidigung des Anwenders senkt."
    },
    "Omega Ruby": {
      "de": "Starke Attacke, die jedoch auch den Angriff und die Verteidigung des Anwenders senkt.",
      "en": "Unknown"
    },
    "Alpha Sapphire": {
      "de": "Starke Attacke, die jedoch auch den Angriff und die Verteidigung des Anwenders senkt.",
      "en": "Unknown"
    }
  }
}