{
  "index_number": 428,
  "pp": 15,
  "max_pp": 24,
  "power": 80,
  "accuracy": 90,
  "category": "physical",
  "priority": 0,
  "target": "target",
  "critical_hit": 0,
  "makes_contact": true,
  "affected_by_protect": true,
  "affected_by_magic_coat": false,
  "affected_by_snatch": false,
  "affected_by_mirror_move": false,
  "affected_by_kings_rock": true,
  "names": {
    "fr": "Psykoud'Boul",
    "de": "Zen-Kopfstoß",
    "gr": "Κεφαλιά Διαφωτισμού",
    "it": "Cozzata Zen",
    "pl": "Taran Zen",
    "en": "Zen Headbutt"
  },
  "descriptions": {
    "en": "The user focuses its willpower to its head and rams the foe. It may also make the target flinch.",
    "de": "Richtet Schaden an und lässt das Ziel mit einer Wahrscheinlichkeit von 20% zurückschrecken. Die Attacke Delegator und die Fähigkeit Konzentrator verhindern ein Zurückschrecken."
  },
  "type": "Psychic"
}